adapters/__init__.py
adapters/aws/__init__.py
adapters/langgraph/__init__.py
adapters/mcp/__init__.py
adapters/mcp/client.py
examples/__init__.py
examples/basic_calculator/__init__.py
examples/devops_incident/__init__.py
examples/minimal_e2e/__init__.py
examples/minimal_e2e/manifest.yaml
examples/minimal_e2e/run.py
examples/repo_assistant/__init__.py
universal_agent/__init__.py
universal_agent/contracts.py
universal_agent/graph/__init__.py
universal_agent/graph/engine.py
universal_agent/graph/model.py
universal_agent/graph/signals.py
universal_agent/graph/state.py
universal_agent/manifests/__init__.py
universal_agent/manifests/loader.py
universal_agent/manifests/schema.py
universal_agent/manifests/validator.py
universal_agent/memory/__init__.py
universal_agent/memory/context_manager.py
universal_agent/memory/stores/__init__.py
universal_agent/observer/__init__.py
universal_agent/observer/sinks/__init__.py
universal_agent/observer/sinks/otel.py
universal_agent/policy/__init__.py
universal_agent/policy/engine.py
universal_agent/router/__init__.py
universal_agent/router/selector.py
universal_agent/router/strategies/__init__.py
universal_agent/runtime/__init__.py
universal_agent/runtime/api.py
universal_agent/runtime/cli.py
universal_agent/runtime/config.py
universal_agent/runtime/defaults.py
universal_agent/runtime/handlers.py
universal_agent/runtime/registry.py
universal_agent/runtime/sandbox.py
universal_agent/task/__init__.py
universal_agent/task/manager.py
universal_agent/task/queue.py
universal_agent/task/store.py
universal_agent/tools/__init__.py
universal_agent/tools/registry.py
universal_agent/tools/protocols/__init__.py
universal_agent_arch-0.3.0.dist-info/METADATA
universal_agent_arch-0.3.0.dist-info/WHEEL
universal_agent_arch-0.3.0.dist-info/entry_points.txt
universal_agent_arch-0.3.0.dist-info/RECORD
