Metadata-Version: 2.4
Name: universal-agent-arch
Version: 0.3.0
Summary: The Kernel for Durable, Declarative AI Agents.
Requires-Python: >=3.11
Requires-Dist: aiosqlite>=0.19.0
Requires-Dist: fastapi>=0.115.0
Requires-Dist: opentelemetry-api>=1.20.0
Requires-Dist: opentelemetry-sdk>=1.20.0
Requires-Dist: pydantic>=2.9.0
Requires-Dist: pyyaml>=6.0
Requires-Dist: sqlalchemy>=2.0.0
Requires-Dist: typer>=0.12.0
Requires-Dist: uvicorn>=0.30.0
Provides-Extra: aws
Requires-Dist: aioboto3>=13.0.0; extra == 'aws'
Requires-Dist: boto3>=1.34.0; extra == 'aws'
Provides-Extra: dev
Requires-Dist: pytest-asyncio>=0.23.0; extra == 'dev'
Requires-Dist: pytest>=8.0.0; extra == 'dev'
Requires-Dist: ruff>=0.6.0; extra == 'dev'
Provides-Extra: langgraph
Requires-Dist: langchain-core>=0.2.0; extra == 'langgraph'
Requires-Dist: langgraph>=0.2.0; extra == 'langgraph'
Provides-Extra: mcp
Requires-Dist: httpx>=0.27.0; extra == 'mcp'
Requires-Dist: mcp>=0.1.0; extra == 'mcp'
